skuidsphinx/VERSION
skuidsphinx/__init__.py
skuidsphinx/__init__.pyc
skuidsphinx/algolia.html
skuidsphinx/footer.html
skuidsphinx/globaltoc.html
skuidsphinx/landingpage.html
skuidsphinx/layout.html
skuidsphinx/localtoc.html
skuidsphinx/mobile-globaltoc.html
skuidsphinx/mobile-localtoc.html
skuidsphinx/navbar.html
skuidsphinx/navbarsearchbox.html
skuidsphinx/page-buttons.html
skuidsphinx/relations.html
skuidsphinx/search.html
skuidsphinx/searchbox.html
skuidsphinx/searchresults.html
skuidsphinx/theme.conf
skuidsphinx/universal-header.html
skuidsphinx/version-header-warnings.html
skuidsphinx/version-select-api.html
skuidsphinx/version-select.html
skuidsphinx/_styles/myriadpro.style
skuidsphinx/analytics/all-analytics.html
skuidsphinx/analytics/fullstory.html
skuidsphinx/analytics/google-analytics.html
skuidsphinx/analytics/hubspot.html
skuidsphinx/analytics/intercom-messenger.html
skuidsphinx/analytics/marketo.html
skuidsphinx/static/basic-skuid.css_t
skuidsphinx/static/bootstrap-theme.css_t
skuidsphinx/static/bootstrap.css_t
skuidsphinx/static/skuid-ink-icons.css_t
skuidsphinx/static/skuid.css_t
skuidsphinx/static/fonts/skuid-ink.eot
skuidsphinx/static/fonts/skuid-ink.svg
skuidsphinx/static/fonts/skuid-ink.ttf
skuidsphinx/static/fonts/skuid-ink.woff
skuidsphinx/static/icons/apps.svg
skuidsphinx/static/icons/developer-resources.svg
skuidsphinx/static/icons/facebook.png
skuidsphinx/static/icons/guides.svg
skuidsphinx/static/icons/instagram.png
skuidsphinx/static/icons/linkedin.png
skuidsphinx/static/icons/tutorials.svg
skuidsphinx/static/icons/twitter.png
skuidsphinx/static/icons/user-reference.svg
skuidsphinx/static/img/green-pattern.svg
skuidsphinx/static/img/ocean-fill.svg
skuidsphinx/static/img/select.png
skuidsphinx/static/img/skuid_logo_white.png
skuidsphinx/static/js/bootstrap.js
skuidsphinx/static/js/jquery-1.11.0.min.js
skuidsphinx/static/js/jquery-fix.js
skuidsphinx/static/js/skuid-sphinx.js
SkuidSphinxTheme-1.0.23.dist-info/METADATA
SkuidSphinxTheme-1.0.23.dist-info/WHEEL
SkuidSphinxTheme-1.0.23.dist-info/entry_points.txt
SkuidSphinxTheme-1.0.23.dist-info/top_level.txt
SkuidSphinxTheme-1.0.23.dist-info/zip-safe
SkuidSphinxTheme-1.0.23.dist-info/RECORD
