Metadata-Version: 2.1
Name: SkuidSphinxTheme
Version: 1.0.23
Summary: Sphinx Theme for Skuid
Home-page: https://github.com/skuid/SkuidSphinxTheme
Author: Shannon Hale
Author-email: shannon@skuid.com
License: UNKNOWN
Keywords: skuid,documentation
Platform: UNKNOWN
Classifier: Topic :: Documentation :: Sphinx
Classifier: Framework :: Sphinx :: Theme
